LICENSE
MANIFEST.in
README.rst
buildout.cfg
requirements.txt
setup.py
version.txt
bob/__init__.py
bob.db.drionsdb.egg-info/PKG-INFO
bob.db.drionsdb.egg-info/SOURCES.txt
bob.db.drionsdb.egg-info/dependency_links.txt
bob.db.drionsdb.egg-info/entry_points.txt
bob.db.drionsdb.egg-info/not-zip-safe
bob.db.drionsdb.egg-info/requires.txt
bob.db.drionsdb.egg-info/top_level.txt
bob/db/__init__.py
bob/db/drionsdb/__init__.py
bob/db/drionsdb/checkfiles.py
bob/db/drionsdb/create.py
bob/db/drionsdb/drionsdb_db_default.json
bob/db/drionsdb/drionsdb_test.csv
bob/db/drionsdb/drionsdb_train.csv
bob/db/drionsdb/driver.py
bob/db/drionsdb/models.py
bob/db/drionsdb/query.py
bob/db/drionsdb/test.py
doc/guide.rst
doc/index.rst
doc/links.rst
doc/py_api.rst
doc/img/bob-128x128.png
doc/img/bob-favicon.ico
doc/img/bob-logo.png